hyphen/__init__.py
hyphen/dictools.py
hyphen/hnj.abi3.so
hyphen/hyphenator.py
hyphen/textwrap2.py
PyHyphen_Reloaded-4.0.6.dist-info/AUTHORS
PyHyphen_Reloaded-4.0.6.dist-info/LICENSE.txt
PyHyphen_Reloaded-4.0.6.dist-info/METADATA
PyHyphen_Reloaded-4.0.6.dist-info/WHEEL
PyHyphen_Reloaded-4.0.6.dist-info/top_level.txt
PyHyphen_Reloaded-4.0.6.dist-info/RECORD
