Metadata-Version: 2.1
Name: PyHyphen-Reloaded
Version: 4.0.6
Summary: The hyphenation library of LibreOffice and FireFox wrapped for Python
Home-page: https://github.com/rakuri255/PyHyphen-Reloaded
Author: Dr. Leo & Regis Behmo & rakuri255
Author-email: fhaxbox66@googlemail.com
Classifier: Intended Audience :: Developers
Classifier: License :: OSI Approved :: Apache Software License
Classifier: Development Status :: 4 - Beta
Classifier: Operating System :: OS Independent
Classifier: Programming Language :: Python
Classifier: Programming Language :: Python :: 3.7
Classifier: Programming Language :: Python :: 3.8
Classifier: Programming Language :: Python :: 3.9
Classifier: Programming Language :: C
Classifier: Topic :: Text Processing
Classifier: Topic :: Text Processing :: Linguistic
License-File: LICENSE.txt
License-File: AUTHORS
Requires-Dist: wheel >=0.43.0
Requires-Dist: setuptools >=70.3.0
Requires-Dist: appdirs >=1.4.4
Requires-Dist: requests >=2.32.3
